ghpro/__init__.py
ghpro/api.py
ghpro/backport.py
ghpro/stats.py
ghpro/utils.py
ghpro-1.1.1.dist-info/DESCRIPTION.rst
ghpro-1.1.1.dist-info/METADATA
ghpro-1.1.1.dist-info/RECORD
ghpro-1.1.1.dist-info/WHEEL
ghpro-1.1.1.dist-info/entry_points.txt
ghpro-1.1.1.dist-info/metadata.json
ghpro-1.1.1.dist-info/pbr.json
ghpro-1.1.1.dist-info/top_level.txt
