Metadata-Version: 2.0
Name: ghpro
Version: 1.1.1
Summary: (IPython/Jupyter) GitHub project tools
Home-page: https://github.com/minrk/ghpro
Author: Min RK, Jupyter Contributors
Author-email: benjaminrk@gmail.com
License: BSD-2-Clause
Keywords: github
Platform: UNKNOWN
Classifier: Development Status :: 3 - Alpha
Classifier: Environment :: Console
Classifier: Intended Audience :: Developers
Classifier: License :: OSI Approved :: BSD License
Classifier: Operating System :: OS Independent
Classifier: Programming Language :: Python
Requires-Dist: gitpython
Requires-Dist: keyring
Requires-Dist: requests
Requires-Dist: requests-cache
